[
  {
    "desafio": 0,
    "xp": 0,
    "nome": "Dragao Azul Adulta",
    "tipo": null,
    "tamanho": null,
    "tendencia": null,
    "pontosDeVida": 0,
    "classeArmadura": null,
    "atributo": null,
    "deslocamento": null,
    "idiomas": [
      {
        "idioma": "elfico"
      }
    ],
    "resistencia_dano": null,
    "teste_resistencia": null,
    "imunidades": null,
    "tracos_especiais": null,
    "acao": null,
    "vulnerabilidades": null,
    "sentidos": null,
    "reacoes": null,
    "equipamentos": null,
    "acaoLendarias": null
  }

]